CIDataPortal/CIDataPortal.py
CIDataPortal/__init__.py
CIDataPortal-1.0.0.dist-info/LICENSE
CIDataPortal-1.0.0.dist-info/METADATA
CIDataPortal-1.0.0.dist-info/WHEEL
CIDataPortal-1.0.0.dist-info/top_level.txt
CIDataPortal-1.0.0.dist-info/RECORD
