Metadata-Version: 2.1
Name: CIDataPortal
Version: 1.0.0
Summary: Package for accessing the NG ESO Carbon Intensity API
Home-page: https://github.com/AyrtonB/Carbon-Intensity-Data-Portal
Author: Ayrton Bourn
Author-email: AyrtonBourn@Outlook.com
License: UNKNOWN
Platform: UNKNOWN
Classifier: Programming Language :: Python :: 3
Classifier: License :: OSI Approved :: MIT License
Classifier: Operating System :: OS Independent
Requires-Python: >=3.6
